[ {
  "id" : "ef47961c-f7f2-8584-7106-0ab95fe66fa7",
  "name" : "logo",
  "label" : "Logo",
  "required" : false,
  "locked" : false,
  "show_loading" : false,
  "type" : "logo",
  "display_width" : null,
  "default" : {
    "override_inherited_src" : true,
    "src" : "https://243368611.fs1.hubspotusercontent-na2.net/hubfs/243368611/logo.png",
    "alt" : "Positivus logo",
    "suppress_company_name" : true,
    "width" : 440,
    "height" : 112
  }
}, {
  "id" : "e93bf484-f522-fdb1-4f41-9ad672d151d5",
  "name" : "navigation_menu",
  "label" : "Navigation menu",
  "required" : false,
  "locked" : false,
  "type" : "menu",
  "display_width" : null,
  "default" : 230495735542
}, {
  "id" : "724bf547-5c9d-c163-46dd-13c70d7a1366",
  "name" : "cta_button",
  "label" : "CTA Button",
  "required" : false,
  "locked" : false,
  "supported_types" : [ "EXTERNAL", "FILE", "CONTENT", "BLOG", "PAYMENT", "EMAIL_ADDRESS", "PHONE_NUMBER" ],
  "show_advanced_rel_options" : false,
  "type" : "link",
  "display_width" : null,
  "default" : {
    "url" : {
      "content_id" : null,
      "type" : "EXTERNAL",
      "href" : ""
    },
    "open_in_new_tab" : false,
    "no_follow" : false
  }
} ]